dataset_loader/__init__.py
dataset_loader/dataset.py
dataset_loader/loader/__init__.py
dataset_loader/loader/partition_loader.py
dataset_loader-1.6.dist-info/LICENSE
dataset_loader-1.6.dist-info/METADATA
dataset_loader-1.6.dist-info/WHEEL
dataset_loader-1.6.dist-info/top_level.txt
dataset_loader-1.6.dist-info/RECORD
