Metadata-Version: 2.1
Name: dataset-loader
Version: 1.6
Summary: Load partitioned data from multilevel folder structure
Home-page: https://github.com/andreclaudino/dataset_loader
Author: André Claudino
License: Type license() to see the full license text
Platform: UNKNOWN
Requires-Dist: pandas
